{
    "taskDefinitionArn": "arn:aws:ecs:ap-south-1:878774248183:task-definition/frontend:3",
    "containerDefinitions": [
        {
            "name": "webserver",
            "image": "878774248183.dkr.ecr.ap-south-1.amazonaws.com/kiran921996:latest",
            "cpu": 0,
            "portMappings": [
                {
                    "name": "frontend-port",
                    "containerPort": 80,
                    "hostPort": 80,
                    "protocol": "tcp",
                    "appProtocol": "http"
                }
            ],
            "essential": true,
            "environment": [],
            "mountPoints": [],
            "volumesFrom": [],
            "logConfiguration": {
                "logDriver": "awslogs",
                "options": {
                    "awslogs-create-group": "true",
                    "awslogs-group": "/ecs/frontend",
                    "awslogs-region": "ap-south-1",
                    "awslogs-stream-prefix": "ecs"
                }
            },
            "healthCheck": {
                "command": [
                    "CMD-SHELL",
                    "curl -f http://localhost:80/ || exit 0"
                ],
                "interval": 30,
                "timeout": 5,
                "retries": 3
            },
            "systemControls": []
        }
    ],
    "family": "frontend",
    "taskRoleArn": "arn:aws:iam::878774248183:role/ecsTaskExecutionRole",
    "executionRoleArn": "arn:aws:iam::878774248183:role/ecsTaskExecutionRole",
    "networkMode": "awsvpc",
    "revision": 3,
    "volumes": [],
    "status": "ACTIVE",
    "requiresAttributes": [
        {
            "name": "com.amazonaws.ecs.capability.logging-driver.awslogs"
        },
        {
            "name": "com.amazonaws.ecs.capability.docker-remote-api.1.24"
        },
        {
            "name": "ecs.capability.execution-role-awslogs"
        },
        {
            "name": "com.amazonaws.ecs.capability.ecr-auth"
        },
        {
            "name": "com.amazonaws.ecs.capability.docker-remote-api.1.19"
        },
        {
            "name": "com.amazonaws.ecs.capability.task-iam-role"
        },
        {
            "name": "ecs.capability.container-health-check"
        },
        {
            "name": "ecs.capability.execution-role-ecr-pull"
        },
        {
            "name": "com.amazonaws.ecs.capability.docker-remote-api.1.18"
        },
        {
            "name": "ecs.capability.task-eni"
        },
        {
            "name": "com.amazonaws.ecs.capability.docker-remote-api.1.29"
        }
    ],
    "placementConstraints": [],
    "compatibilities": [
        "EC2",
        "FARGATE"
    ],
    "requiresCompatibilities": [
        "FARGATE"
    ],
    "cpu": "1024",
    "memory": "2048",
    "runtimePlatform": {
        "cpuArchitecture": "X86_64",
        "operatingSystemFamily": "LINUX"
    },
    "registeredAt": "2024-04-16T07:28:08.614Z",
    "registeredBy": "arn:aws:iam::878774248183:root",
    "tags": []
}
